setup.py
src/gs2/__init__.py
src/gs2.egg-info/PKG-INFO
src/gs2.egg-info/SOURCES.txt
src/gs2.egg-info/dependency_links.txt
src/gs2.egg-info/requires.txt
src/gs2.egg-info/top_level.txt
src/gs2/account/__init__.py
src/gs2/account/model.py
src/gs2/account/request.py
src/gs2/account/rest.py
src/gs2/account/result.py
src/gs2/account/web_socket.py
src/gs2/ad_reward/__init__.py
src/gs2/ad_reward/model.py
src/gs2/ad_reward/request.py
src/gs2/ad_reward/rest.py
src/gs2/ad_reward/result.py
src/gs2/ad_reward/web_socket.py
src/gs2/auth/__init__.py
src/gs2/auth/model.py
src/gs2/auth/request.py
src/gs2/auth/rest.py
src/gs2/auth/result.py
src/gs2/auth/web_socket.py
src/gs2/buff/__init__.py
src/gs2/buff/model.py
src/gs2/buff/request.py
src/gs2/buff/rest.py
src/gs2/buff/result.py
src/gs2/buff/web_socket.py
src/gs2/chat/__init__.py
src/gs2/chat/model.py
src/gs2/chat/request.py
src/gs2/chat/rest.py
src/gs2/chat/result.py
src/gs2/chat/web_socket.py
src/gs2/core/__init__.py
src/gs2/core/exception.py
src/gs2/core/model.py
src/gs2/core/rest.py
src/gs2/core/util.py
src/gs2/core/web_socket.py
src/gs2/core/domain/__init__.py
src/gs2/core/domain/access_token.py
src/gs2/datastore/__init__.py
src/gs2/datastore/model.py
src/gs2/datastore/request.py
src/gs2/datastore/rest.py
src/gs2/datastore/result.py
src/gs2/datastore/web_socket.py
src/gs2/deploy/__init__.py
src/gs2/deploy/model.py
src/gs2/deploy/request.py
src/gs2/deploy/rest.py
src/gs2/deploy/result.py
src/gs2/deploy/web_socket.py
src/gs2/dictionary/__init__.py
src/gs2/dictionary/model.py
src/gs2/dictionary/request.py
src/gs2/dictionary/rest.py
src/gs2/dictionary/result.py
src/gs2/dictionary/web_socket.py
src/gs2/distributor/__init__.py
src/gs2/distributor/model.py
src/gs2/distributor/request.py
src/gs2/distributor/rest.py
src/gs2/distributor/result.py
src/gs2/distributor/web_socket.py
src/gs2/enchant/__init__.py
src/gs2/enchant/model.py
src/gs2/enchant/request.py
src/gs2/enchant/rest.py
src/gs2/enchant/result.py
src/gs2/enchant/web_socket.py
src/gs2/enhance/__init__.py
src/gs2/enhance/model.py
src/gs2/enhance/request.py
src/gs2/enhance/rest.py
src/gs2/enhance/result.py
