Metadata-Version: 2.1
Name: gs2
Version: 1.1.244
Summary: GS2 SDK for Python.
Home-page: https://gs2.io/
Author: Game Server Services, Inc.
Author-email: contact@gs2.io
License: Apache License 2.0
Platform: UNKNOWN
Classifier: Programming Language :: Python
Classifier: Programming Language :: Python :: 3
Classifier: Programming Language :: Python :: 3.6
